dbtk/__init__.py
dbtk/__main__.py
dbtk/_utils.py
dbtk/cli/__init__.py
dbtk/cli/_cli.py
dbtk/cli/subcommands/__init__.py
dbtk/cli/subcommands/data.py
dbtk/cli/subcommands/model.py
dbtk/cli/subcommands/wandb.py
dbtk/config/__init__.py
dbtk/data/__init__.py
dbtk/data/datasets.py
dbtk/data/interfaces.py
dbtk/data/tokenizers.py
dbtk/data/vocabularies.py
dbtk/data/samplers/__init__.py
dbtk/data/samplers/abundance.py
dbtk/data/transforms/__init__.py
dbtk/data/transforms/compositions.py
dbtk/loggers/__init__.py
dbtk/loggers/wandb.py
dbtk/nn/callbacks.py
dbtk/nn/functional.py
dbtk/nn/layers.py
dbtk/nn/models/__init__.py
dbtk/nn/models/bert.py
deepbio_toolkit-0.4.5.dist-info/licenses/LICENSE
deepbio_toolkit-0.4.5.dist-info/METADATA
deepbio_toolkit-0.4.5.dist-info/WHEEL
deepbio_toolkit-0.4.5.dist-info/entry_points.txt
deepbio_toolkit-0.4.5.dist-info/top_level.txt
deepbio_toolkit-0.4.5.dist-info/RECORD
