Metadata-Version: 2.4
Name: deepbio-toolkit
Version: 0.4.5
Summary: A collection of various deep-learning and data handling tools for running and building deep-learning models for computational biology.
Author-email: "David W. Ludwig II" <davidludwigii@gmail.com>
License: MIT License
Project-URL: Homepage, https://github.com/DLii-Research/deepbio-toolkit
Project-URL: Bug Tracker, https://github.com/DLii-Research/deepbio-toolkit/issues
Requires-Python: >=3.8
License-File: LICENSE
Requires-Dist: attn-gym
Requires-Dist: bitarray==3.0.0
Requires-Dist: deflate
Requires-Dist: Deprecated
Requires-Dist: explainable-attention
Requires-Dist: lightning[pytorch-extra]
Requires-Dist: numba>=0.59.1
Requires-Dist: tqdm
Requires-Dist: torch>=2.5.0
Dynamic: license-file
